{
	"module": "@solenopsys/lt-website",
	"state": {
		"ui": {
			"top": "@solenopsys/ui-navigate:UiTopPane",
			"menu": "@solenopsys/ui-layouts:UiTreeMenu"
		},
		"page": {
			"favicon": "/images/favicon.svg",
			"title": "Solenopsys vc",
			"logo": "/images/logo.svg"
		},
		"navigation": {
			"selected": "/",
			"tree": [
				{
					"id": "/",
					"title": "Main"
				},
				{
					"id": "/technology/",
					"title": "Technology"
				},
				{
					"id": "/solenopsys/",
					"title": "Solenopsys"
				}
			]
		},
		"routes": {
			"/": {
				"center": {
					"component": "@solenopsys/mf-landing:HwLanding",
					"props": {
						"ipfs": "bafyreiem4ua7r2ulj5dpwyjwakxpvitebr4kqqf2qxaorwmqlulmr4hm7q"
					}
				},
				"left": null
			},
			"/technology/": {
				"center": {
					"component": "@solenopsys/mf-content:MdDynamic",
					"props": {
						"ipfs": "bafyreiawvvl2pixk5ptfjpzvdewgqct2ipdl6y6lryhqqjtxqcnhu4cciu"
					}
				},
				"left": {
					"component": "@solenopsys/mf-content:MainMenu",
					"props": {
						"ipfs": "bafyreidgpojvygao3pkllr7gugl5x7t3sef3zrpmzzwdbmovljzrptxf7q"
					}
				}
			},
			"/solenopsys/": {
				"center": {
					"component": "@solenopsys/mf-content:MdDynamic",
					"props": {
						"ipfs": "bafyreicbj53krv45c623bw42eehanjfpg2ga3fjst6rbhnjuwljyl3ufpm"
					}
				},
				"left": {
					"component": "@solenopsys/mf-content:MainMenu",
					"props": {
						"ipfs": "bafyreifflffavxtfpdgdoo7ejxl26memep425rgtm4basefainujilizii"
					}
				}
			}
		}
	}
}
